pygeoflow/__init__.py
pygeoflow/aggregation.py
pygeoflow/export.py
pygeoflow/join.py
pygeoflow/logger.py
pygeoflow/models.py
pygeoflow/parser.py
pygeoflow/preperation.py
pygeoflow/spatial_operations.py
pygeoflow/utilities.py
pygeoflow/workflow.py
pygeoflow-0.0.1.dist-info/LICENSE
pygeoflow-0.0.1.dist-info/METADATA
pygeoflow-0.0.1.dist-info/WHEEL
pygeoflow-0.0.1.dist-info/entry_points.txt
pygeoflow-0.0.1.dist-info/top_level.txt
pygeoflow-0.0.1.dist-info/RECORD
