Metadata-Version: 2.1
Name: pygeoflow
Version: 0.0.1
Summary: A python package that helps you create geographic workflows within a cloud data warehouse. 
Home-page: https://github.com/mkeller3/pygeoflow
Author: Michael Keller
Author-email: michaelkeller03@gmail.com
License: MIT License
Classifier: License :: OSI Approved :: MIT License
Classifier: Programming Language :: Python :: 3
License-File: LICENSE
Requires-Dist: annotated-types ==0.6.0
Requires-Dist: psycopg2 ==2.9.9
Requires-Dist: pydantic ==2.6.1
Requires-Dist: pydantic-core ==2.16.2
Requires-Dist: typing-extensions ==4.9.0
Requires-Dist: pytest ==8.0.0
Requires-Dist: coverage ==7.4.1
